frequenz/sdk/__init__.py
frequenz/sdk/py.typed
frequenz/sdk/_api_client/__init__.py
frequenz/sdk/_api_client/api_client.py
frequenz/sdk/_internal/__init__.py
frequenz/sdk/_internal/_asyncio.py
frequenz/sdk/_internal/_constants.py
frequenz/sdk/_internal/_math.py
frequenz/sdk/_internal/_singleton_meta.py
frequenz/sdk/actor/__init__.py
frequenz/sdk/actor/_actor.py
frequenz/sdk/actor/_background_service.py
frequenz/sdk/actor/_channel_registry.py
frequenz/sdk/actor/_config_managing.py
frequenz/sdk/actor/_resampling.py
frequenz/sdk/actor/_run_utils.py
frequenz/sdk/actor/_data_sourcing/__init__.py
frequenz/sdk/actor/_data_sourcing/data_sourcing.py
frequenz/sdk/actor/_data_sourcing/microgrid_api_source.py
frequenz/sdk/actor/power_distributing/__init__.py
frequenz/sdk/actor/power_distributing/_battery_pool_status.py
frequenz/sdk/actor/power_distributing/_battery_status.py
frequenz/sdk/actor/power_distributing/power_distributing.py
frequenz/sdk/actor/power_distributing/request.py
frequenz/sdk/actor/power_distributing/result.py
frequenz/sdk/actor/power_distributing/_distribution_algorithm/__init__.py
frequenz/sdk/actor/power_distributing/_distribution_algorithm/_distribution_algorithm.py
frequenz/sdk/config/__init__.py
frequenz/sdk/config/_config.py
frequenz/sdk/microgrid/__init__.py
frequenz/sdk/microgrid/_data_pipeline.py
frequenz/sdk/microgrid/_graph.py
frequenz/sdk/microgrid/connection_manager.py
frequenz/sdk/microgrid/client/__init__.py
frequenz/sdk/microgrid/client/_client.py
frequenz/sdk/microgrid/client/_connection.py
frequenz/sdk/microgrid/client/_retry.py
frequenz/sdk/microgrid/component/__init__.py
frequenz/sdk/microgrid/component/_component.py
frequenz/sdk/microgrid/component/_component_data.py
frequenz/sdk/microgrid/component/_component_states.py
frequenz/sdk/timeseries/__init__.py
frequenz/sdk/timeseries/_base_types.py
frequenz/sdk/timeseries/_moving_window.py
frequenz/sdk/timeseries/_periodic_feature_extractor.py
frequenz/sdk/timeseries/_quantities.py
frequenz_sdk-0.25.2.dist-info/LICENSE
frequenz_sdk-0.25.2.dist-info/METADATA
frequenz_sdk-0.25.2.dist-info/WHEEL
frequenz_sdk-0.25.2.dist-info/top_level.txt
frequenz_sdk-0.25.2.dist-info/RECORD
