Metadata-Version: 2.1
Name: frequenz-sdk
Version: 0.25.2
Summary: A development kit to interact with the Frequenz development platform
Author-email: Frequenz Energy-as-a-Service GmbH <floss@frequenz.com>
License: MIT
Project-URL: Changelog, https://github.com/frequenz-floss/frequenz-sdk-python/releases
Project-URL: Issues, https://github.com/frequenz-floss/frequenz-sdk-python/issues
Project-URL: Repository, https://github.com/frequenz-floss/frequenz-sdk-python
Project-URL: Support, https://github.com/frequenz-floss/frequenz-sdk-python/discussions/categories/support
Keywords: frequenz,python,lib,library,sdk,microgrid
Classifier: Development Status :: 3 - Alpha
Classifier: Intended Audience :: Developers
Classifier: License :: OSI Approved :: MIT License
Classifier: Programming Language :: Python :: 3
Classifier: Programming Language :: Python :: 3 :: Only
Classifier: Topic :: Software Development :: Libraries
Classifier: Typing :: Typed
Requires-Python: <4,>=3.11
License-File: LICENSE
Requires-Dist: frequenz-api-microgrid <0.16.0,>=0.15.1
Requires-Dist: frequenz-channels <0.17.0,>=0.16.0
Requires-Dist: google-api-python-client <3,>=2.71
Requires-Dist: grpcio <2,>=1.54.2
Requires-Dist: grpcio-tools <2,>=1.54.2
Requires-Dist: networkx <4,>=2.8
Requires-Dist: numpy <2,>=1.24.2
Requires-Dist: protobuf <5,>=4.21.6
Requires-Dist: pydantic <2,>=1.9
Requires-Dist: tqdm <5,>=4.38.0
Requires-Dist: typing-extensions <5,>=4.4.0
Requires-Dist: watchfiles >=0.15.0
Provides-Extra: dev
Requires-Dist: frequenz-sdk[dev-docstrings,dev-formatting,dev-mkdocs,dev-mypy,dev-noxfile,dev-pylint,dev-pytest] ; extra == 'dev'
Provides-Extra: dev-docstrings
Requires-Dist: pydocstyle ==6.3.0 ; extra == 'dev-docstrings'
Requires-Dist: darglint ==1.8.1 ; extra == 'dev-docstrings'
Requires-Dist: tomli ==2.0.1 ; extra == 'dev-docstrings'
Provides-Extra: dev-examples
Requires-Dist: polars ==0.18.15 ; extra == 'dev-examples'
Provides-Extra: dev-formatting
Requires-Dist: black ==23.7.0 ; extra == 'dev-formatting'
Requires-Dist: isort ==5.12.0 ; extra == 'dev-formatting'
Provides-Extra: dev-mkdocs
Requires-Dist: mike ==1.1.2 ; extra == 'dev-mkdocs'
Requires-Dist: mkdocs-gen-files ==0.5.0 ; extra == 'dev-mkdocs'
Requires-Dist: mkdocs-literate-nav ==0.6.0 ; extra == 'dev-mkdocs'
Requires-Dist: mkdocs-material ==9.2.5 ; extra == 'dev-mkdocs'
Requires-Dist: mkdocs-section-index ==0.3.5 ; extra == 'dev-mkdocs'
Requires-Dist: mkdocstrings[python] ==0.22.0 ; extra == 'dev-mkdocs'
Requires-Dist: frequenz-repo-config[lib] ==0.5.2 ; extra == 'dev-mkdocs'
Provides-Extra: dev-mypy
Requires-Dist: mypy ==1.5.1 ; extra == 'dev-mypy'
Requires-Dist: grpc-stubs ==1.24.12 ; extra == 'dev-mypy'
Requires-Dist: types-protobuf ==4.24.0.1 ; extra == 'dev-mypy'
Requires-Dist: frequenz-sdk[dev-mkdocs,dev-noxfile,dev-pytest] ; extra == 'dev-mypy'
Provides-Extra: dev-noxfile
Requires-Dist: nox ==2023.4.22 ; extra == 'dev-noxfile'
Requires-Dist: frequenz-repo-config[lib] ==0.5.2 ; extra == 'dev-noxfile'
Provides-Extra: dev-pylint
Requires-Dist: pylint ==2.17.5 ; extra == 'dev-pylint'
Requires-Dist: frequenz-sdk[dev-mkdocs,dev-noxfile,dev-pytest] ; extra == 'dev-pylint'
Provides-Extra: dev-pytest
Requires-Dist: pytest ==7.4.0 ; extra == 'dev-pytest'
Requires-Dist: frequenz-repo-config[extra-lint-examples] ==0.5.2 ; extra == 'dev-pytest'
Requires-Dist: pytest-mock ==3.11.1 ; extra == 'dev-pytest'
Requires-Dist: pytest-asyncio ==0.21.1 ; extra == 'dev-pytest'
Requires-Dist: time-machine ==2.12.0 ; extra == 'dev-pytest'
Requires-Dist: async-solipsism ==0.5 ; extra == 'dev-pytest'
Requires-Dist: sybil ==5.0.3 ; extra == 'dev-pytest'
Requires-Dist: pylint ==2.17.5 ; extra == 'dev-pytest'
Requires-Dist: frequenz-sdk[dev-examples] ; extra == 'dev-pytest'
